pycliboilerplate/__init__.py
pycliboilerplate/cli.py
pycliboilerplate/logger.py
pycliboilerplate-0.3.1.dist-info/METADATA
pycliboilerplate-0.3.1.dist-info/WHEEL
pycliboilerplate-0.3.1.dist-info/entry_points.txt
pycliboilerplate-0.3.1.dist-info/licenses/LICENSE
pycliboilerplate-0.3.1.dist-info/RECORD
