Metadata-Version: 2.4
Name: pycliboilerplate
Version: 0.3.1
Summary: A minimal Python CLI boilerplate template for GitHub-hosted projects.
Project-URL: Homepage, https://github.com/JustusRijke/py-cli-boilerplate
Project-URL: Issues, https://github.com/JustusRijke/py-cli-boilerplate/issues
Author-email: Justus Rijke <justusrijke@gmail.com>
License-Expression: MIT
License-File: LICENSE
Classifier: Development Status :: 4 - Beta
Classifier: Operating System :: Microsoft :: Windows
Classifier: Operating System :: POSIX :: Linux
Classifier: Programming Language :: Python :: 3
Requires-Python: >=3.10
Requires-Dist: click
Requires-Dist: colorlog
Provides-Extra: dev
Requires-Dist: pytest; extra == 'dev'
Requires-Dist: pytest-cov; extra == 'dev'
Requires-Dist: ruff; extra == 'dev'
